fastpix/__init__.py
fastpix/async_client/__init__.py
fastpix/async_client/api.py
fastpix/async_client/client.py
fastpix/async_client/live_streams.py
fastpix/async_client/media.py
fastpix/async_client/playback_ids.py
fastpix/client/__init__.py
fastpix/client/api.py
fastpix/client/client.py
fastpix/client/live_streams.py
fastpix/client/media.py
fastpix/client/playback_ids.py
fastpix/utilis/__init__.py
fastpix/utilis/constants.py
fastpix/utilis/exceptions.py
fastpix-11.9.0.dist-info/METADATA
fastpix-11.9.0.dist-info/WHEEL
fastpix-11.9.0.dist-info/top_level.txt
fastpix-11.9.0.dist-info/RECORD
